tree_sitter_zsh/__init__.py
tree_sitter_zsh/__init__.pyi
tree_sitter_zsh/_binding.abi3.so
tree_sitter_zsh/binding.c
tree_sitter_zsh/py.typed
tree_sitter_zsh/queries/highlights.scm
tree_sitter_zsh-0.53.0.dist-info/METADATA
tree_sitter_zsh-0.53.0.dist-info/WHEEL
tree_sitter_zsh-0.53.0.dist-info/top_level.txt
tree_sitter_zsh-0.53.0.dist-info/RECORD
tree_sitter_zsh-0.53.0.dist-info/licenses/LICENSE
