Metadata-Version: 2.4
Name: tree-sitter-zsh
Version: 0.53.0
Summary: Zsh grammar for tree-sitter
Author-email: George Harker <georgeharker@gmail.com>
License: MIT
Project-URL: Homepage, https://github.com/georgeharker/tree-sitter-zsh
Keywords: incremental,parsing,tree-sitter,zsh
Classifier: Intended Audience :: Developers
Classifier: License :: OSI Approved :: MIT License
Classifier: Topic :: Software Development :: Compilers
Classifier: Topic :: Text Processing :: Linguistic
Classifier: Typing :: Typed
Requires-Python: >=3.10
License-File: LICENSE
Provides-Extra: core
Requires-Dist: tree-sitter~=0.24; extra == "core"
Dynamic: license-file
